windowjack/__init__.py
windowjack/capture.py
windowjack-2.0.0.dist-info/METADATA
windowjack-2.0.0.dist-info/WHEEL
windowjack-2.0.0.dist-info/top_level.txt
windowjack-2.0.0.dist-info/RECORD
