Metadata-Version: 2.4
Name: windowjack
Version: 2.0.0
Summary: Windows screen and window capture library with occlusion support
Author: WindowJack
Requires-Python: >=3.7
Requires-Dist: numpy
Provides-Extra: dev
Requires-Dist: pytest; extra == "dev"
Requires-Dist: pillow; extra == "dev"
Dynamic: author
Dynamic: requires-python
